ipmimonitoring/__init__.py
ipmimonitoring/__main__.py
ipmimonitoring/_argparse_helper.py
ipmimonitoring/_cffi_helper.py
ipmimonitoring/arguments.py
ipmimonitoring/bitmasks.py
ipmimonitoring/enums.py
ipmimonitoring/offsets.py
ipmimonitoring/py.typed
ipmimonitoring/wrapper.py
ipmimonitoring-0.1.2.dist-info/licenses/LICENSE
ipmimonitoring-0.1.2.dist-info/WHEEL
ipmimonitoring-0.1.2.dist-info/METADATA
ipmimonitoring-0.1.2.dist-info/RECORD
