Metadata-Version: 2.4
Name: ipmimonitoring
Version: 0.1.2
Summary: A python wrapper for libipmimonitoring from freeipmi
Author: Christer Weinigel
Author-email: Christer Weinigel <christer@weinigel.se>
License-Expression: MIT
License-File: LICENSE
Requires-Dist: cffi>=1.15.1
Requires-Dist: prettytable>=3.10.0
Requires-Python: >=3.8
Project-URL: homepage, https://github.com/wingel/ipmimonitoring
Project-URL: repository, https://github.com/wingel/ipmimonitoring.git
